pseudonymizer_uk/__init__.py
pseudonymizer_uk/pseudonymizer.py
pseudonymizer_uk-0.1.3.dist-info/METADATA
pseudonymizer_uk-0.1.3.dist-info/WHEEL
pseudonymizer_uk-0.1.3.dist-info/licenses/LICENSE
pseudonymizer_uk-0.1.3.dist-info/RECORD
