Metadata-Version: 2.4
Name: pseudonymizer-uk
Version: 0.1.3
Summary: A Python library for pseudonymizing Ukrainian text using Presidio analyzer with Ukrainian NER model
Project-URL: Homepage, https://github.com/fox-rudie/pseudonymizer-uk
Project-URL: Repository, https://github.com/fox-rudie/pseudonymizer-uk.git
Project-URL: Bug Tracker, https://github.com/fox-rudie/pseudonymizer-uk/issues
Author-email: Rudie <ruda.andrii@gmail.com>
License-Expression: MIT
License-File: LICENSE
Classifier: Development Status :: 3 - Alpha
Classifier: Intended Audience :: Developers
Classifier: License :: OSI Approved :: MIT License
Classifier: Natural Language :: Ukrainian
Classifier: Programming Language :: Python :: 3
Classifier: Programming Language :: Python :: 3.9
Requires-Python: <3.10,>=3.9
Requires-Dist: presidio-analyzer>=2.2.355
Requires-Dist: presidio-anonymizer>=2.2.355
Requires-Dist: spacy-transformers==1.3.8
Requires-Dist: spacy==v3.7.4
Provides-Extra: dev
Requires-Dist: black>=24.0.0; extra == 'dev'
Requires-Dist: pytest>=8.0.0; extra == 'dev'
Requires-Dist: ruff>=0.3.0; extra == 'dev'
